agenticwerx_mcp_client/__init__.py
agenticwerx_mcp_client/__main__.py
agenticwerx_mcp_client/api.py
agenticwerx_mcp_client/client.py
agenticwerx_mcp_client-1.0.5.dist-info/METADATA
agenticwerx_mcp_client-1.0.5.dist-info/WHEEL
agenticwerx_mcp_client-1.0.5.dist-info/entry_points.txt
agenticwerx_mcp_client-1.0.5.dist-info/licenses/LICENSE
agenticwerx_mcp_client-1.0.5.dist-info/RECORD
